{
  "name": "Nettie Abbott",
  "age": 18,
  "address": {
    "street": "Dagi Turnpike",
    "city": "Ogsagzi",
    "state": "SD",
    "zip": "63853"
  },
  "contact": {
    "phone": "(208) 765-2677",
    "servicePhone": "800759348"
  },
  "birthday": "2003-11-10T07:00:22.409Z",
  "ip": "62.227.12.179",
  "foo": "bar",
  "profile": {
    "about": "Huawumu nuot cew amvug eririhdej kambek zaezahek jiadzis mafto zitopohel jijot ivoofmaz de zubez vi. Id gi woze novobe goanos wi kewlaspa opow heli baage vuben rim. Dod emipo vuki nahujecu gak in gu mu ba lulfu decjuf wav vo uliuhejo tihummu.",
    "bio": "Ri sogijmiz vozfup ipadat bevzahip hahvim orihahwu meb said nur ocezemu romgafiv he oh ki. Hakiwo puidu bire vibo fug cawdupa de mazehow cuv ru ehulos fokulu itebub ti sevaf ve ar fehawre. Idafidsa hek fek cagolo gihco punafal gi jehudi zoc buit ocbi ter ihjuvru wowta bipwohko ca cuajopi. Celihza gijleje sohtuhko buffolju ba tunfabga memnub fiahe tuzze siw gajzamri ude sem kadvir seuvo."
  },
  "apiKey": "05c7fb9d578df4f8120cec6f3c4f117b355cb01ae0f95bc2f5b644a02b30533e",
  "currency": {
    "code": "GEL",
    "name": "Georgia Lari"
  }
}