{
  "name": "Eugene Bowen",
  "age": 45,
  "address": {
    "street": "Sokuk River",
    "city": "Ralasiv",
    "state": "AK",
    "zip": "63327"
  },
  "contact": {
    "phone": "(565) 774-7167",
    "servicePhone": "800475958"
  },
  "birthday": "2000-05-27T09:48:07.003Z",
  "ip": "153.120.230.238",
  "foo": "bar",
  "profile": {
    "about": "Kuogu jejuzu ejinul iku lo ihozahlis wuprooco cogob ewusauvi bizuvef hirna mus. Ruewo tu ro kemsulul fonrov wiw hihdurmil epimo veji ognoftew dujoku raet pen. Vo uja puszu isabuag ocmu gogikvic jot jadoc mavmedin wu jatog moisoeva hupwe. Koza redofiv loim si zef hurkilwe nimoncaj nitagzaw odomih cinopfuj datnu neahweg san mu dofta dohacdo. Toatuso cuvu ogwi itas vuprim edaoguho gugasumuj rosjetub ziboto jocam va mifisbe cocamo. Hounvum zi kicu nejit nuf mo upece ji id met viw ditelfof rewte. Julago sajuwi bouha ohnevje goso fozholvab pusawho poilecef mirsohe cezi co emu.",
    "bio": "Kiz no nev oh vo hinoti avila lipa jeh hef luddowla al mupemofu. Mumna kutme jiz ah lum vaze gedegke das sut jicuv kasgo cumaw cula bi ca ebelri zun. Zithaghef jawuhid zufir ca wo ud vuwosup lehoj ci uzlijor cohkekig tuz. Lezijzu utube joemomo pivfaot ikifafav ugpu taszafij mi zuv juzkazzeh gael hedaru puwafacah tomras san iwkog fi wujteefo. Uzihuhe keha ira zaja mevwuas uj tan bu idit wu udivippip zikjewev ilde. Foblibej sartezpo gegsikege cicu uf ugu necutuku zozuzav fah ce si dov gum telga."
  },
  "apiKey": "8ae2aa87413fc783040fa4f7a3926642824f128b28c22cc21ae7ef1e3fc10681",
  "currency": {
    "code": "LKR",
    "name": "Sri Lanka Rupee"
  }
}